pygeckodriver/__init__.py
pygeckodriver/geckodriver_aarch64
pygeckodriver/geckodriver_linux32
pygeckodriver/geckodriver_linux64
pygeckodriver/geckodriver_macos
pygeckodriver/geckodriver_win32.exe
pygeckodriver/geckodriver_win64.exe
pygeckodriver-0.33.0.dist-info/LICENSE
pygeckodriver-0.33.0.dist-info/METADATA
pygeckodriver-0.33.0.dist-info/WHEEL
pygeckodriver-0.33.0.dist-info/top_level.txt
pygeckodriver-0.33.0.dist-info/RECORD
